{
    "function": [
        {
            "functionName": [
                {
                    "term": "EDAM_operation:2429", 
                    "uri": "http://edamontology.org/operation_2429"
                }
            ]
        }, 
        {
            "functionName": [
                {
                    "term": "EDAM_operation:2520", 
                    "uri": "http://edamontology.org/operation_2520"
                }
            ]
        }, 
        {
            "functionName": [
                {
                    "term": "EDAM_operation:0523", 
                    "uri": "http://edamontology.org/operation_0523"
                }
            ]
        }, 
        {
            "functionName": [
                {
                    "term": "EDAM_operation:0310", 
                    "uri": "http://edamontology.org/operation_0310"
                }
            ]
        }
    ], 
    "name": "DeleteRegions", 
    "credits": {
        "creditsDeveloper": [
            "Boeva V", 
            " Surdez D", 
            " Guillon N", 
            " Tirode F", 
            " Fejes AP", 
            " Delattre O", 
            " Barillot E."
        ]
    }, 
    "resourceType": [
        {
            "term": "tool"
        }
    ], 
    "docs": [], 
    "collection": [
        "micsa"
    ], 
    "topic": [
        {
            "term": "EDAM_topic:0196", 
            "uri": "http://edamontology.org/topic_0196"
        }
    ], 
    "affiliation": "Gensoft @Institut Pasteur", 
    "contact": [
        {
            "contactEmail": "gensoft@pasteur.fr", 
            "contactTel": "", 
            "contactURL": "", 
            "contactName": "", 
            "contactRole": [
                "Technical"
            ]
        }
    ], 
    "publications": {
        "publicationsOtherID": [], 
        "publicationsPrimaryID": "10.1093/nar/gkq217"
    }, 
    "version": "1.0", 
    "interface": [
        {
            "interfaceType": {
                "term": "Command line", 
                "uri": "http://www.cbs.dtu.dk/ontology/interface_type/5"
            }
        }
    ], 
    "homepage": "http://bioinfo-out.curie.fr/projects/micsa/", 
    "description": "Identification of transcription factor binding sites in ChIP-Seq data"
}