{
    "function": [
        {
            "term": "EDAM_operation:0004", 
            "uri": "http://edamontology.org/operation_0004"
        }
    ], 
    "name": "prinseq-lite.pl", 
    "credits": {
        "creditsDeveloper": [
            "Schmieder R.", 
            " Edwards R."
        ]
    }, 
    "resourceType": [
        {
            "term": "tool"
        }
    ], 
    "docs": [], 
    "collection": [
        "prinseq"
    ], 
    "topic": [
        {
            "term": "EDAM_topic:0157", 
            "uri": "http://edamontology.org/topic_0157"
        }, 
        {
            "term": "EDAM_topic:0220", 
            "uri": "http://edamontology.org/topic_0220"
        }
    ], 
    "affiliation": "Gensoft @Institut Pasteur", 
    "contact": [
        {
            "contactEmail": "gensoft@pasteur.fr", 
            "contactTel": "", 
            "contactURL": "", 
            "contactName": "", 
            "contactRole": [
                "Technical"
            ]
        }
    ], 
    "version": "0.20.3", 
    "interface": [
        {
            "interfaceType": {
                "term": "Command line", 
                "uri": "http://www.cbs.dtu.dk/ontology/interface_type/5"
            }
        }
    ], 
    "homepage": "http://prinseq.sourceforge.net/", 
    "description": " PRINSEQ can be used to filter, reformat, or trim your genomic and metagenomic sequence data. It generates summary statistics of your sequences in graphical and tabular format"
}