{
    "collectionName": "GalaxyAtPasteur", 
    "sourceRegistry": "toolshed-pasteur", 
    "description": "", 
    "platform": "Linux", 
    "maturity": "production", 
    "version": "1.56.0", 
    "softwareType": "Tool", 
    "id": "galaxy.web.pasteur.fr/toolshed-pasteur/repos/fmareuil/picard_pasteur_wrapper/rgEstLibComp/1.56.0", 
    "fonction": {
        "outputs": [
            {
                "label": "${out_prefix}_lib_complexity.html", 
                "name": "html_file", 
                "format": "html"
            }
        ], 
        "functionHandle": "MainFunction", 
        "description": "", 
        "inputs": [
            {
                "label": "SAM/BAM dataset", 
                "type": "data", 
                "name": "input_file", 
                "format": "bam,sam"
            }
        ]
    }, 
    "name": "Estimate Library Complexity"
}